{
	"name": "KenFoodPrice",
	"properties": {
		"type": "MappingDataFlow",
		"typeProperties": {
			"sources": [
				{
					"dataset": {
						"referenceName": "ds_KenFoodPrice_copied",
						"type": "DatasetReference"
					},
					"name": "source1"
				}
			],
			"sinks": [
				{
					"dataset": {
						"referenceName": "ds_KenFoodPrice_DBTarget",
						"type": "DatasetReference"
					},
					"name": "sink1"
				}
			],
			"transformations": [],
			"scriptLines": [
				"source(output(",
				"          date as string,",
				"          admin1 as string,",
				"          admin2 as string,",
				"          market as string,",
				"          latitude as string,",
				"          longitude as string,",
				"          category as string,",
				"          commodity as string,",
				"          unit as string,",
				"          priceflag as string,",
				"          pricetype as string,",
				"          currency as string,",
				"          price as string,",
				"          usdprice as string",
				"     ),",
				"     allowSchemaDrift: true,",
				"     validateSchema: false,",
				"     ignoreNoFilesFound: false) ~> source1",
				"source1 sink(allowSchemaDrift: true,",
				"     validateSchema: false,",
				"     deletable:false,",
				"     insertable:true,",
				"     updateable:true,",
				"     upsertable:false,",
				"     format: 'table',",
				"     skipDuplicateMapInputs: true,",
				"     skipDuplicateMapOutputs: true) ~> sink1"
			]
		}
	}
}